{
  "relationshipIndicators": {
    "primary": {
      "position": "primary",
      "label": "offered by",
      "tags": [
        {
          "class": "ma__relationship-indicators--term",
          "href": "#",
          "title": "Department of Conservation and Recreation"
        },
        {
          "class": "ma__relationship-indicators--term",
          "href": "#",
          "title": "Other agency or organization"
        }
      ]
    },
    "secondary": {
      "position": "",
      "label": "related to",
      "tags": [
        {
          "class": "ma__relationship-indicators--term",
          "href": "#",
          "title": "Snowmobile in the Parks"
        },
        {
          "class": "ma__relationship-indicators--term",
          "href": "#",
          "title": "Cross-Country Skiing"
        },
        {
          "class": "ma__relationship-indicators--term",
          "href": "#",
          "title": "Accessible Hiking"
        },
        {
          "class": "ma__relationship-indicators--term",
          "href": "#",
          "title": "Scenic Viewing Areas"
        },
        {
          "class": "ma__relationship-indicators--term",
          "href": "#",
          "title": "Hunting"
        },
        {
          "class": "ma__relationship-indicators--term",
          "href": "#",
          "title": "Biking"
        }
      ]
    }
  },
  "pageBanner": {
    "bgWide": "../../assets/images/placeholder/820x460.png",
    "bgNarrow": "../../assets/images/placeholder/800x400.png",
    "size": "columns",
    "icon": "lg-picnic-table",
    "title": "State Parks & Recreation",
    "description": "First line of this Topic that feeds description on cards.  This description can span multiple lines."
  },
  "utilityNav": {
    "items": [
      {
        "id": "stateOrgs",
        "text": "State Organizations",
        "ariaLabelText": "",
        "icon": "@atoms/05-icons/svg-building.twig",
        "closeText": "Close",
        "panels": [
          {
            "description": {
              "richText": {
                "rteElements": [
                  {
                    "path": "@atoms/11-text/paragraph.twig",
                    "data": {
                      "paragraph": {
                        "text": "The <a href=\"#\">A-Z Organizations page</a> provides an alphabetical listing of government organizations, including commissions, departments, and bureaus."
                      }
                    }
                  }
                ]
              }
            },
            "links": ""
          }
        ]
      },
      {
        "id": "logInTo",
        "text": "Log in to...",
        "ariaLabelText": "Log in links for this page",
        "icon": "@atoms/05-icons/svg-login.twig",
        "closeText": "Close",
        "panels": [
          {
            "description": {
              "richText": {
                "rteElements": [
                  {
                    "path": "@atoms/11-text/paragraph.twig",
                    "data": {
                      "paragraph": {
                        "text": "Login links for this page"
                      }
                    }
                  }
                ]
              }
            },
            "links": [
              {
                "text": "Contextual Login 1",
                "href": "#",
                "type": "external"
              },
              {
                "text": "Contextual Login 2",
                "href": "",
                "type": "external"
              }
            ]
          },
          {
            "description": {
              "richText": {
                "rteElements": [
                  {
                    "path": "@atoms/11-text/paragraph.twig",
                    "data": {
                      "paragraph": {
                        "text": "These are the top requested sites you can log in to access state provided services"
                      }
                    }
                  }
                ]
              }
            },
            "links": [
              {
                "text": "Unemployment Online",
                "href": "https://uionline.detma.org/Claimant/Core/Login.ASPX",
                "type": "external"
              },
              {
                "text": "Virtual Gateway (SNAP)",
                "href": "https://sso.hhs.state.ma.us/oam/server/obrareq.cgi?encquery%3DA2%2Fmo5AkZreDycpyP0JZAEOYGvW2hviyNhH9Sht2xPp0V1%2BBtWfHnmRGr6zNHOqOlcjphPk7p6bpHHRyNzzk9IYQ%2FcN%2B%2FIcqL2ThnI217OsIKZepptTpGBx83SI0NWjsE7vDi72caItXWlelbGQT7ePanlrVUUy2%2Fj1UEUaXi5G7m47KO9djBnoetZRCtp9G2ZTNFf6zvCGU7Cs02AXYUj2JMH4aqol%2Bh3OK6uhJNNkFvwQ1MFRUa4gR1az4iaW9u83ExKb2a9eDv8ZIUqhlq3%2BNVGTqZHAsHX4KOONSGQRBwCtLNPWwruacjdd9CaEqeIJ2tnP45KrM93edZ6zU1yoWGbAp%2BUWWMqk4HyrtuA8%3D%20agentid%3Dwebgate1%20ver%3D1%20crmethod%3D2",
                "type": "external"
              },
              {
                "text": "Child Support Enforcement",
                "href": "https://ecse.cse.state.ma.us/ECSE/Login/login.asp",
                "type": "external"
              },
              {
                "text": "MassTaxConnect",
                "href": "https://mtc.dor.state.ma.us/mtc/_/",
                "type": "external"
              },
              {
                "text": "myRmv",
                "href": "https://atlas-myrmv.massdot.state.ma.us/myrmv/",
                "type": "external"
              },
              {
                "text": "Massachusetts Health Connector",
                "href": "https://www.mahealthconnector.org/",
                "type": "external"
              },
              {
                "text": "Massachusetts Juror Service Website",
                "href": "https://juryduty.majury.gov/ojcweb/public/start.aspx",
                "type": "external"
              },
              {
                "text": "Find a Commonwealth Job ",
                "href": "https://massanf.taleo.net/careersection/ex/jobsearch.ftl",
                "type": "external"
              }
            ]
          }
        ]
      }
    ]
  },
  "sectionThreeUp": {
    "compHeading": null,
    "sections": [
      {
        "id": "GUIDasjdhf1",
        "catIcon": "",
        "title": {
          "href": "#",
          "text": "Recreation Service"
        },
        "description": "First line of this Service that helps users know it's right.",
        "type": "callout",
        "links": [
          {
            "href": "#",
            "text": "Service How-To 1"
          },
          {
            "href": "#",
            "text": "Service Task 2"
          }
        ],
        "seeAll": {
          "href": "#",
          "text": "More about this service",
          "info": "learn more about the Recreation Service"
        }
      },
      {
        "id": "GUIDasjdhf2",
        "catIcon": "",
        "title": {
          "href": "#",
          "text": "Active & Team Sports"
        },
        "description": "First line of this Topic that feeds descriptions on cards.  Additional overview information augue ante, egestas nec semper.",
        "links": [
          {
            "href": "#",
            "text": "Ice Skating"
          },
          {
            "href": "#",
            "text": "Golfing"
          },
          {
            "href": "#",
            "text": "Reserve an Athletic Field"
          }
        ],
        "seeAll": {
          "href": "#",
          "text": "More about this topic",
          "info": "learn more about Active & Team Sports"
        }
      },
      {
        "id": "GUIDasjdhf3",
        "catIcon": "",
        "title": {
          "href": "/patterns/05-pages-L2-nature-and-outdoor-activities/05-pages-L2-nature-and-outdoor-activities.html",
          "text": "Nature & Outdoor Activities"
        },
        "description": "First line of this Topic that feeds descriptions on cards.  Additional overview information augue ante, egestas nec semper.",
        "links": [
          {
            "href": "#",
            "text": "Camping"
          },
          {
            "href": "#",
            "text": "Hiking"
          },
          {
            "href": "#",
            "text": "Biking"
          }
        ],
        "seeAll": {
          "href": "#",
          "text": "More about this topic",
          "info": "learn more about Nature & Outdoor Activities"
        }
      },
      {
        "id": "GUIDasjdhf4",
        "catIcon": "",
        "title": {
          "href": "#",
          "text": "Water Related Activities"
        },
        "description": "First line of this Topic that feeds descriptions on cards.  Additional overview information augue ante, egestas nec semper.",
        "links": [
          {
            "href": "#",
            "text": "Boating"
          },
          {
            "href": "#",
            "text": "Lifeguarding"
          },
          {
            "href": "#",
            "text": "Canoeing"
          }
        ],
        "seeAll": {
          "href": "#",
          "text": "More about this topic"
        }
      }
    ],
    "seeAll": {
      "href": "#",
      "text": "More about this",
      "info": "learn more about Water Related Activities"
    }
  },
  "relatedOrgsAndTopics": {
    "header": {
      "title": "Related Information",
      "level": "2"
    },
    "columns": [
      {
        "column_title": "Organizations",
        "linkList": {
          "compHeading": {
            "title": "Organizations",
            "level": "3"
          },
          "stacked": true,
          "links": [
            {
              "href": "#",
              "text": "Related Organization #1"
            },
            {
              "href": "#",
              "text": "Related Organization #2"
            },
            {
              "href": "#",
              "text": "Related Organization #3"
            },
            {
              "href": "#",
              "text": "Executive Office of Health and Human Services"
            },
            {
              "href": "#",
              "text": "Related Organization #5"
            },
            {
              "href": "#",
              "text": "Related Organization #6"
            },
            {
              "href": "#",
              "text": "Related Organization #7"
            },
            {
              "href": "#",
              "text": "Board of Registration in Allied Mental Health and Human Services Professions"
            },
            {
              "href": "#",
              "text": "Related Organization #9"
            },
            {
              "href": "#",
              "text": "Board of Registration of Professional Engineers and Professional Land Surveyors "
            },
            {
              "href": "#",
              "text": "Massachusetts Commission on Lesbian, Gay, Bisexual, Transgender, Queer and Questioning Youth"
            },
            {
              "href": "#",
              "text": "Related Organization #12"
            }
          ]
        }
      },
      {
        "column_title": "Topics",
        "linkList": {
          "compHeading": {
            "title": "Topics",
            "level": "3"
          },
          "stacked": true,
          "links": [
            {
              "href": "#",
              "text": "Related Topic #1"
            },
            {
              "href": "#",
              "text": "Related Topic #2"
            },
            {
              "href": "#",
              "text": "Related Topic #3"
            }
          ]
        }
      }
    ]
  }
}
