  {
  "pageBanner": {
    "image": "../../assets/images/placeholder/2x1.png",
    "imageMobile": "../../assets/images/placeholder/2x1.png",
    "imageMedium": "../../assets/images/placeholder/4x3.png",
    "theme": "c-primary-alt",
    "showMobileImage": true,
    "pageHeader": {
      "title": "Governor Maura Healey and Lt. Governor Kim Driscoll",
      "fullWidthAddon": true,
      "optionalContents": [{
        "path": "@organisms/by-author/rich-text.twig",
        "data": {
          "richText": {
            "rteElements": [{
              "path": "atoms-paragraph",
              "data": {
                "paragraph" : {
                  "text": "The Commonwealth of Massachusetts welcomes new residents to enjoy all the state has to offer. To help make your move to the Bay State as smooth as possible, this guide provides instructions for changing your license, tips for settling in, and other useful information."
                }
              }
            }]
          }
        }
      }]
    }
  }
}
